google/cloud/monitoring/__init__.py
google/cloud/monitoring/gapic_version.py
google/cloud/monitoring/py.typed
google/cloud/monitoring_v3/__init__.py
google/cloud/monitoring_v3/_dataframe.py
google/cloud/monitoring_v3/gapic_metadata.json
google/cloud/monitoring_v3/gapic_version.py
google/cloud/monitoring_v3/py.typed
google/cloud/monitoring_v3/query.py
google/cloud/monitoring_v3/services/__init__.py
google/cloud/monitoring_v3/services/alert_policy_service/__init__.py
google/cloud/monitoring_v3/services/alert_policy_service/async_client.py
google/cloud/monitoring_v3/services/alert_policy_service/client.py
google/cloud/monitoring_v3/services/alert_policy_service/pagers.py
google/cloud/monitoring_v3/services/alert_policy_service/transports/__init__.py
google/cloud/monitoring_v3/services/alert_policy_service/transports/base.py
google/cloud/monitoring_v3/services/alert_policy_service/transports/grpc.py
google/cloud/monitoring_v3/services/alert_policy_service/transports/grpc_asyncio.py
google/cloud/monitoring_v3/services/group_service/__init__.py
google/cloud/monitoring_v3/services/group_service/async_client.py
google/cloud/monitoring_v3/services/group_service/client.py
google/cloud/monitoring_v3/services/group_service/pagers.py
google/cloud/monitoring_v3/services/group_service/transports/__init__.py
google/cloud/monitoring_v3/services/group_service/transports/base.py
google/cloud/monitoring_v3/services/group_service/transports/grpc.py
google/cloud/monitoring_v3/services/group_service/transports/grpc_asyncio.py
google/cloud/monitoring_v3/services/metric_service/__init__.py
google/cloud/monitoring_v3/services/metric_service/async_client.py
google/cloud/monitoring_v3/services/metric_service/client.py
google/cloud/monitoring_v3/services/metric_service/pagers.py
google/cloud/monitoring_v3/services/metric_service/transports/__init__.py
google/cloud/monitoring_v3/services/metric_service/transports/base.py
google/cloud/monitoring_v3/services/metric_service/transports/grpc.py
google_cloud_monitoring-2.27.1.dist-info/LICENSE
google_cloud_monitoring-2.27.1.dist-info/METADATA
google_cloud_monitoring-2.27.1.dist-info/WHEEL
google_cloud_monitoring-2.27.1.dist-info/top_level.txt
google_cloud_monitoring-2.27.1.dist-info/RECORD
